{ 
    "testName": "string", 
    "app": "string", 
    "tier": "string", 
    "node": "string", 
    "agentName": "string",
    "date": "date", 
    "target":"string",
    "connectTime": "integer",
    "errorDetails" : "string",
    "receiveTime": "integer",
    "responseTime": "integer",
    "countryId": "string", 
    "agentId": "integer", 
    "roundId": "integer", 
    "totalSize": "integer", 
    "numObjects": "integer", 
    "numErrors": "integer",
    "domLoadTime": "integer",
    "pageLoadTime": "integer",
    "permalink": "string",
    "dnsTime": "integer",
    "errorType": "string",
    "numRedirects": "integer",
    "responseCode": "integer",
    "serverIp":"string",
    "totalTime": "integer",
    "waitTime": "integer",
    "wireSize": "integer",
    "avgLatency": "float",
    "loss": "float",
    "maxLatency": "float",
    "jitter": "float",
    "minLatency": "float",
    "throughput" : "float"
} 

